imvideo/__init__.py
imvideo-0.0.2.dist-info/LICENSE
imvideo-0.0.2.dist-info/METADATA
imvideo-0.0.2.dist-info/WHEEL
imvideo-0.0.2.dist-info/top_level.txt
imvideo-0.0.2.dist-info/RECORD
