Metadata-Version: 2.1
Name: imvideo
Version: 0.0.2
Summary: Imvideo: Image to video made easy. Powered by OpenCV.
Home-page: https://xli2522.github.io/imvideo/
Author: Xiyuan Li
Author-email: xli2522@uwo.ca
License: UNKNOWN
Keywords: openCV,image to video,python video,matplotlib,time-lapse
Platform: UNKNOWN
Classifier: Programming Language :: Python :: 3
Classifier: License :: OSI Approved :: MIT License
Classifier: Operating System :: OS Independent
Requires-Python: >=3.6
